nb_quality_profile/__init__.py
nb_quality_profile/cli.py
nb_quality_profile/nb_visualiser.py
nb_quality_profile/notebook_profiler.py
nb_quality_profile/text_quality.py
nb_quality_profile/text_stats.py
nb_quality_profile-0.3.4.dist-info/LICENSE
nb_quality_profile-0.3.4.dist-info/METADATA
nb_quality_profile-0.3.4.dist-info/WHEEL
nb_quality_profile-0.3.4.dist-info/entry_points.txt
nb_quality_profile-0.3.4.dist-info/top_level.txt
nb_quality_profile-0.3.4.dist-info/RECORD
