Metadata-Version: 2.1
Name: nb_quality_profile
Version: 0.3.4
Summary: Tools for profiling Jupyter notebook quality and visualing notebook structure.
Author: Tony Hirst
Author-email: tony.hirst@gmail.com
License-File: LICENSE
Requires-Dist: nbformat
Requires-Dist: isort
Requires-Dist: jupytext
Requires-Dist: click
Requires-Dist: deepmerge
Requires-Dist: lxml
Requires-Dist: markdown
Requires-Dist: pandas
Requires-Dist: matplotlib
Requires-Dist: numpy
Requires-Dist: spacy
Requires-Dist: scikit-learn
Requires-Dist: scipy
Requires-Dist: readtime
Requires-Dist: list-imports
Requires-Dist: pytest-codeblocks
Requires-Dist: radon
Requires-Dist: pyflakes
Requires-Dist: seaborn
